django_object_acl/__init__.py
django_object_acl/apps.py
django_object_acl/managers.py
django_object_acl/migrations/0001_initial.py
django_object_acl/migrations/__init__.py
django_object_acl/mixins.py
django_object_acl/models.py
django_object_acl-0.1.2.dist-info/WHEEL
django_object_acl-0.1.2.dist-info/METADATA
django_object_acl-0.1.2.dist-info/RECORD
